BetterLoggin/__init__.py
BetterLoggin/logger.py
BetterLoggin-0.1.4.dist-info/LICENSE
BetterLoggin-0.1.4.dist-info/METADATA
BetterLoggin-0.1.4.dist-info/WHEEL
BetterLoggin-0.1.4.dist-info/top_level.txt
BetterLoggin-0.1.4.dist-info/RECORD
